mediarecommender/__init__.py
mediarecommender/main.py
mediarecommender/itemdatabase/__init__.py
mediarecommender/itemdatabase/data_collection.py
mediarecommender/itemdatabase/data_preprocessing.py
mediarecommender/itemdatabase/feature_extractor.py
mediarecommender/itemdatabase/parameters.py
mediarecommender/itemdatabase/reset_database.py
mediarecommender/itemdatabase/word2vec_trainer.py
mediarecommender/recommender/__init__.py
mediarecommender/recommender/models.py
mediarecommender/recommender/recommender.db
mediarecommender/recommender/recommender.py
mediarecommender/recommender/routes.py
mediarecommender/recommender/__pycache__/__init__.cpython-37.pyc
mediarecommender/recommender/__pycache__/models.cpython-37.pyc
mediarecommender/recommender/__pycache__/recommender.cpython-37.pyc
mediarecommender/recommender/__pycache__/routes.cpython-37.pyc
mediarecommender/recommender/static/giantbomb_icon.png
mediarecommender/recommender/static/goodreads_icon.png
mediarecommender/recommender/static/imdb_icon.png
mediarecommender/recommender/static/main.css
mediarecommender/recommender/static/main.js
mediarecommender/recommender/static/steam_icon.png
mediarecommender/recommender/templates/home.html
mediarecommender/recommender/templates/layout.html
media_recommender-0.0.3.dist-info/METADATA
media_recommender-0.0.3.dist-info/WHEEL
media_recommender-0.0.3.dist-info/top_level.txt
media_recommender-0.0.3.dist-info/RECORD
