Metadata-Version: 2.1
Name: media-recommender
Version: 0.0.3
Summary: Media Recommender provides recommendation for movies, videos games and books
Home-page: https://git-teaching.cs.bham.ac.uk/mod-ug-proj-2018/cxc574
Author: Chung Yin Cheung
Author-email: cxc574@student.bham.ac.uk
License: UNKNOWN
Platform: UNKNOWN
Classifier: Programming Language :: Python :: 3.6
Classifier: Operating System :: OS Independent
Requires-Dist: beautifulsoup4
Requires-Dist: Flask
Requires-Dist: Flask-SQLAlchemy
Requires-Dist: gensim
Requires-Dist: IMDbPY
Requires-Dist: nltk
Requires-Dist: numpy
Requires-Dist: pandas
Requires-Dist: requests
Requires-Dist: scikit-learn
Requires-Dist: SQLAlchemy
Requires-Dist: untangle
